SoftwareEngineeringForInternetApplications/README.md
SoftwareEngineeringForInternetApplications/__init__.py
SoftwareEngineeringForInternetApplications/__main__.py
SoftwareEngineeringForInternetApplications/file.epub
SoftwareEngineeringForInternetApplications/index.html
SoftwareEngineeringForInternetApplications/css/__init__.py
SoftwareEngineeringForInternetApplications/css/annotations.css
SoftwareEngineeringForInternetApplications/css/main.css
SoftwareEngineeringForInternetApplications/css/normalize.css
SoftwareEngineeringForInternetApplications/css/popup.css
SoftwareEngineeringForInternetApplications/font/__init__.py
SoftwareEngineeringForInternetApplications/font/fontello.eot
SoftwareEngineeringForInternetApplications/font/fontello.svg
SoftwareEngineeringForInternetApplications/font/fontello.ttf
SoftwareEngineeringForInternetApplications/font/fontello.woff
SoftwareEngineeringForInternetApplications/img/__init__.py
SoftwareEngineeringForInternetApplications/img/annotator-glyph-sprite.png
SoftwareEngineeringForInternetApplications/img/annotator-icon-sprite.png
SoftwareEngineeringForInternetApplications/img/apple-touch-icon.png
SoftwareEngineeringForInternetApplications/img/cancelfullscreen.png
SoftwareEngineeringForInternetApplications/img/close.png
SoftwareEngineeringForInternetApplications/img/fullscreen.png
SoftwareEngineeringForInternetApplications/img/loader.gif
SoftwareEngineeringForInternetApplications/img/menu-icon.png
SoftwareEngineeringForInternetApplications/img/save.png
SoftwareEngineeringForInternetApplications/img/saved.png
SoftwareEngineeringForInternetApplications/img/settings-s.png
SoftwareEngineeringForInternetApplications/img/settings.png
SoftwareEngineeringForInternetApplications/img/star.png
SoftwareEngineeringForInternetApplications/js/__init__.py
SoftwareEngineeringForInternetApplications/js/epub.js
SoftwareEngineeringForInternetApplications/js/epub.min.js
SoftwareEngineeringForInternetApplications/js/epub.min.map
software_engineering_for_internet_applications-2024.3.2.0.dist-info/METADATA
software_engineering_for_internet_applications-2024.3.2.0.dist-info/WHEEL
software_engineering_for_internet_applications-2024.3.2.0.dist-info/entry_points.txt
software_engineering_for_internet_applications-2024.3.2.0.dist-info/top_level.txt
software_engineering_for_internet_applications-2024.3.2.0.dist-info/RECORD
